[
    {
        "nobility": ["Esquire"],
        "age": ["adult", "elder"],
        "value": "Banker"
    },
    {
        "nobility": ["Esquire", "Noble, Royal"],
        "age": ["elder"],
        "value": "Judge",
        "alignment": [
            "Lawful Good",
            "Neutral Good",
            "Lawful Neutral",
            "True Neutral",
            "Lawful Evil",
            "Neutral Evil"
        ]
    },
    {
        "nobility": ["Esquire", "Noble", "Royal"],
        "age": ["adult", "elder"],
        "value": "Diplomat"
    }
]
